{
    "clasificacion": [{
        "id": 1,
        "nombre": "Deportivo Alavés",
        "imagen": "https://i.ibb.co/5j590tt/alaves.png",
        "PJ": 11,
        "G": 5,
        "E": 4,
        "P": 3,
        "Pts": 18
    }, {
        "id": 2,
        "nombre": "Athletic Club",
        "imagen": "https://i.ibb.co/VBSNb8p/ath.png",
        "PJ": 11,
        "G": 6,
        "E": 2,
        "P": 3,
        "Pts": 20
    }, {
        "id": 3,
        "nombre": "Atlético de Madrid",
        "imagen": "https://i.ibb.co/rQ0HmB7/atm.png",
        "PJ": 11,
        "G": 6,
        "E": 3,
        "P": 2,
        "Pts": 21
    }, {
        "id": 4,
        "nombre": "FC Barcelona",
        "imagen": "https://i.ibb.co/J3wZMHV/fcb.png",
        "PJ": 11,
        "G": 11,
        "E": 0,
        "P": 0,
        "Pts": 33
    }, {
        "id": 5,
        "nombre": "Real Betis",
        "imagen": "https://i.ibb.co/61CsZDg/bet.png",
        "PJ": 11,
        "G": 3,
        "E": 2,
        "P": 6,
        "Pts": 11
    }, {
        "id": 6,
        "nombre": "Eibar",
        "imagen": "https://i.ibb.co/vPZ239h/eibar.png",
        "PJ": 11,
        "G": 4,
        "E": 0,
        "P": 7,
        "Pts": 12
    }, {
        "id": 7,
        "nombre": "Levante UD",
        "imagen": "https://i.ibb.co/QKSWKqg/lud.png",
        "PJ": 11,
        "G": 6,
        "E": 3,
        "P": 2,
        "Pts": 18
    }, {
        "id": 6,
        "nombre": "Madrid CFF",
        "imagen": "https://i.ibb.co/jZML2r0/mad.png",
        "PJ": 11,
        "G": 5,
        "E": 2,
        "P": 4,
        "Pts": 17
    }, {
        "id": 8,
        "nombre": "Rayo Vallecano",
        "imagen": "https://i.ibb.co/svwsm0f/rayo.png",
        "PJ": 11,
        "G": 1,
        "E": 2,
        "P": 8,
        "Pts": 5
    }, {
        "id": 9,
        "nombre": "Real Madrid",
        "imagen": "https://i.ibb.co/t831sKv/rm.png",
        "PJ": 11,
        "G": 4,
        "E": 2,
        "P": 5,
        "Pts": 14
    }, {
        "id": 10,
        "nombre": "Real Sociedad",
        "imagen": "https://i.ibb.co/Fhm307F/real.png",
        "PJ": 11,
        "G": 9,
        "E": 0,
        "P": 2,
        "Pts": 24
    }, {
        "id": 12,
        "nombre": "Sevilla FC",
        "imagen": "https://i.ibb.co/hf7L4wm/sev.png",
        "PJ": 11,
        "G": 4,
        "E": 3,
        "P": 4,
        "Pts": 15
    }, {
        "id": 13,
        "nombre": "Sporting de Huelva",
        "imagen": "https://i.ibb.co/HBxXmBm/spo.png",
        "PJ": 11,
        "G": 0,
        "E": 6,
        "P": 5,
        "Pts": 6
    }, {
        "id": 14,
        "nombre": "UD Granadilla Tenerife",
        "imagen": "https://i.ibb.co/PhCZm7n/udt.png",
        "PJ": 11,
        "G": 6,
        "E": 4,
        "P": 3,
        "Pts": 16
    }, {
        "id": 15,
        "nombre": "Valencia CF",
        "imagen": "https://i.ibb.co/bBfpRPH/vcf.png",
        "PJ": 11,
        "G": 2,
        "E": 2,
        "P": 7,
        "Pts": 8
    }, {
        "id": 16,
        "nombre": "Villareal",
        "imagen": "https://i.ibb.co/wQYbNq4/villareal.png",
        "PJ": 11,
        "G": 1,
        "E": 2,
        "P": 8,
        "Pts": -1
    }]
}